recsys_models/__init__.py
recsys_models/pipeline.py
recsys_models/data/__init__.py
recsys_models/data/sampling.py
recsys_models/models/__init__.py
recsys_models/models/bpr.py
recsys_models/models/fpmc.py
recsys_models/models/transrec.py
recsys_models-0.1.3.dist-info/LICENSE
recsys_models-0.1.3.dist-info/METADATA
recsys_models-0.1.3.dist-info/WHEEL
recsys_models-0.1.3.dist-info/top_level.txt
recsys_models-0.1.3.dist-info/RECORD
