Metadata-Version: 2.1
Name: recsys-models
Version: 0.1.3
Summary: TensorFlow Recommender Systems Models for Implicit Feedback
Home-page: https://github.com/shuyangli94/RecSysModels
Author: Shuyang Li
Author-email: shuyangli94@gmail.com
License: GPLv3+
Keywords: recommender systems,recommender,recommendation system,tensorflow
Platform: UNKNOWN
Classifier: Intended Audience :: Developers
Classifier: Intended Audience :: Education
Classifier: Intended Audience :: Science/Research
Classifier: Topic :: Scientific/Engineering
Classifier: License :: OSI Approved :: BSD License
Classifier: Programming Language :: Python
Classifier: Programming Language :: Python :: 3
Classifier: Programming Language :: Python :: 3.6
Requires-Dist: numpy (>=1.14.5)
Requires-Dist: pandas (>=0.23.3)
